odoo/addons/account_dms_field/README.rst
odoo/addons/account_dms_field/__init__.py
odoo/addons/account_dms_field/__manifest__.py
odoo/addons/account_dms_field/demo/account_dms_data.xml
odoo/addons/account_dms_field/i18n/account_dms_field.pot
odoo/addons/account_dms_field/i18n/it.po
odoo/addons/account_dms_field/models/__init__.py
odoo/addons/account_dms_field/models/account_move.py
odoo/addons/account_dms_field/static/description/icon.png
odoo/addons/account_dms_field/tests/__init__.py
odoo/addons/account_dms_field/tests/test_account_dms_field.py
odoo/addons/account_dms_field/views/account_move_view.xml
odoo_addon_account_dms_field-16.0.1.0.2.1.dist-info/METADATA
odoo_addon_account_dms_field-16.0.1.0.2.1.dist-info/WHEEL
odoo_addon_account_dms_field-16.0.1.0.2.1.dist-info/top_level.txt
odoo_addon_account_dms_field-16.0.1.0.2.1.dist-info/RECORD
