Metadata-Version: 2.1
Name: odoo-addon-account_dms_field
Version: 16.0.1.0.2.1
Summary: Add dms field for account
Home-page: https://github.com/OCA/dms
Author: Agent ERP GmbH, Odoo Community Association (OCA)
Author-email: support@odoo-community.org
License: LGPL-3
Classifier: Programming Language :: Python
Classifier: Framework :: Odoo
Classifier: Framework :: Odoo :: 16.0
Classifier: License :: OSI Approved :: GNU Lesser General Public License v3 (LGPLv3)
Requires-Python: >=3.10
Requires-Dist: odoo-addon-dms-field<16.1dev,>=16.0dev
Requires-Dist: odoo<16.1dev,>=16.0a
